[
    {
        "Duration(minutes)": "",
        "Time": "ROOM 1",
        "Schedule": "Building solutions to breach payment gaps",
        "Speaker/Facilitator": "Tobi Fatunde",
        "Role/Company": "Product Associate, Seerbit",
        "Slides": "",
        "Bio": ""
      },
      {
        "Duration(minutes)": "",
        "Time": "ROOM 2",
        "Schedule": "The Power of Community",
        "Speaker/Facilitator": "Tosin Oyetade",
        "Role/Company": "Growth Marketing ,Cardana Pay",
        "Slides": "https://drive.google.com/file/d/18k5tx92Gy5rUO8fjSb66EeF1tdFB2HbK/view?usp=share_link",
        "Bio": ""
      },
      {
        "Duration(minutes)": "",
        "Time": "ROOM 3",
        "Schedule": "Neuromarketing and Community Management: The Science of Consumers/Users Decisions",
        "Speaker/Facilitator": "Hussein Sanni",
        "Role/Company": "Digital Marketing Executive, Utiva",
        "Slides": "",
        "Bio": ""
      },
      {
        "Duration(minutes)": "",
        "Time": "ROOM 4",
        "Schedule": "A Guide to Product Experimentation",
        "Speaker/Facilitator": "Taslim Okunola",
        "Role/Company": "Product Manager, Chrome at Google",
        "Slides": "https://docs.google.com/presentation/d/1DhsuOLDeoKZtwXVQW7HIeQmYOC_5-xPogxpwOex7GRg/edit?usp=sharing",
        "Bio": ""
      },
      {
        "Duration(minutes)": "",
        "Time": "ROOM 5",
        "Schedule": "Raffle & Benefits of Pillow",
        "Speaker/Facilitator": "Feranmi",
        "Role/Company": "",
        "Slides": "",
        "Bio": ""
      },
      {
        "Duration(minutes)": "",
        "Time": "ROOM 6",
        "Schedule": "",
        "Speaker/Facilitator": "",
        "Role/Company": "",
        "Slides": "",
        "Bio": ""
      }
]